__init__.py
your_code.py
my_oleksii3-2.0.0.dist-info/METADATA
my_oleksii3-2.0.0.dist-info/WHEEL
my_oleksii3-2.0.0.dist-info/top_level.txt
my_oleksii3-2.0.0.dist-info/RECORD
