Metadata-Version: 2.4
Name: my_oleksii3
Version: 2.0.0
Summary: my_oleksii3
Author-email: Oleksii Saiun <oleksiisaiun@example.com>
Requires-Python: >=3.10
